dealer/__init__.py
dealer/auto.py
dealer/base.py
dealer/env.py
dealer/git.py
dealer/mercurial.py
dealer/null.py
dealer/simple.py
dealer/contrib/__init__.py
dealer/contrib/flask.py
dealer/contrib/pyramid.py
dealer/contrib/django/__init__.py
dealer/contrib/django/settings.py
dealer/contrib/django/staff.py
dealer-2.1.0.dist-info/AUTHORS
dealer-2.1.0.dist-info/LICENSE
dealer-2.1.0.dist-info/METADATA
dealer-2.1.0.dist-info/WHEEL
dealer-2.1.0.dist-info/top_level.txt
dealer-2.1.0.dist-info/RECORD
