Metadata-Version: 2.1
Name: dealer
Version: 2.1.0
Summary: Dealer -- SCM (Git, Mercurial) watcher
